DomFu/__init__.py
DomFu/__main__.py
DomFu/modules/__init__.py
DomFu/modules/Probe/__init__.py
DomFu/modules/Probe/probe.py
DomFu/modules/Spies/BufferOverRun.py
DomFu/modules/Spies/HackerTarget.py
DomFu/modules/Spies/ThreatCrowd.py
DomFu/modules/Spies/VirusTotal.py
DomFu/modules/Spies/__init__.py
DomFu/modules/Spies/chaos.py
DomFu/modules/Spies/crtsh.py
DomFu/modules/Spies/shodan.py
DomFu/modules/Spies/subdomain.py
DomFu-1.3.0.dist-info/LICENSE.txt
DomFu-1.3.0.dist-info/METADATA
DomFu-1.3.0.dist-info/WHEEL
DomFu-1.3.0.dist-info/entry_points.txt
DomFu-1.3.0.dist-info/top_level.txt
DomFu-1.3.0.dist-info/RECORD
