Metadata-Version: 2.1
Name: DomFu
Version: 1.3.0
Summary: A CLI app to find domains and subdomains of a given domain
Home-page: http://pypi.python.org/pypi/domfu/
Author: Suman Basuli
Author-email: thinisadhu@gmail.com
License: LICENSE.txt
Platform: UNKNOWN
License-File: LICENSE.txt
Requires-Dist: click
Requires-Dist: yaspin
Requires-Dist: requests
Requires-Dist: requests[socks]
Requires-Dist: requests[security]
